{"id":"demande-de-constitution-d'une-commission-speciale","nom":"demande de constitution d'une commission spéciale","id_an":null,"metrics":{},"seances":[{"id":"1163","sommaire":[],"parlementaires":{"Yves Jégo":1},"personnalites":{},"interventions":[{"id":"175952","seance_id":"1163","date":"2018-04-03","moment":"09:30","type":"elocution","titre":"demande de constitution d'une commission spéciale","titre_complet":"demande de constitution d'une commission spéciale","timestamp":"40","intervention":"<p>L'Assemblée a été informée de la demande de constitution d'une commission spéciale présentée par le président du groupe de la Gauche démocrate et républicaine pour l'examen de la proposition de loi portant suppression de la prise en compte des revenus du conjoint dans la base de calcul de l'allocation aux adultes handicapés.</p><p>Une opposition formulée par la présidente de la commission des affaires sociales est parvenue à la présidence. L'Assemblée sera donc appelée à statuer sur la demande de constitution d'une commission spéciale. Il appartiendra à la Conférence des présidents de fixer l'horaire de ce débat.</p>","nb_mots":107,"nom":"NULL","parlementaire":"Yves Jégo","sexe":"H","parlementaire_groupe_acronyme":"UAI","fonction":"président","source":"http://www.assemblee-nationale.fr/15/cri/2017-2018/20180173.asp#P1217974","groupes":["présidence"],"nb_cars":627,"nb_excl":0,"nb_qust":0,"nb_phrs":3,"nb_mwbp":209,"interruption":false}],"nb_cars":627,"nb_mots":107,"nb_excl":0,"nb_interruptions":0,"pc_interruptions":0},{"id":"1200","sommaire":[],"parlementaires":{"Annie Genevard":9,"Jean Lassalle":3,"Brigitte Bourguignon":3,"Valérie Rabault":1,"André Chassaigne":10,"Isabelle Valentin":1,"Gilles Lurton":2},"personnalites":{},"interventions":[{"id":"176763","seance_id":"1200","date":"2018-04-03","moment":"15:00","type":"elocution","titre":"demande de constitution d'une commission spéciale","titre_complet":"demande de constitution d'une commission spéciale","timestamp":"4900","intervention":"<p>L'ordre du jour appelle la décision de l'Assemblée sur la demande de constitution d'une commission spéciale.</p><p>Je rappelle que le président du groupe de la Gauche démocrate et républicaine a demandé que la proposition de loi portant suppression de la prise en compte des revenus du conjoint dans la base de calcul de l'allocation aux adultes handicapés, renvoyée à la commission des affaires sociales, fasse l'objet d'une commission spéciale.</p><p>Une opposition a été formulée par la présidente de la commission des affaires sociales. L'Assemblée est appelée à se prononcer sur cette demande, dans les conditions prévues à l'article 31, alinéa 4, de notre règlement.</p>","nb_mots":118,"nom":"NULL","parlementaire":"Annie Genevard","sexe":"F","parlementaire_groupe_acronyme":"LR","fonction":"présidente","source":"http://www.assemblee-nationale.fr/15/cri/2017-2018/20180174.asp#P1219300","groupes":["présidence"],"nb_cars":679,"nb_excl":0,"nb_qust":0,"nb_phrs":2,"nb_mwbp":339.5,"interruption":false},{"id":"176764","seance_id":"1200","date":"2018-04-03","moment":"15:00","type":"elocution","titre":"demande de constitution d'une commission spéciale","titre_complet":"demande de constitution d'une commission spéciale","timestamp":"4910","intervention":"<p>J'écoute Chassaigne et je m'en vais !</p>","nb_mots":10,"nom":"NULL","parlementaire":"Jean Lassalle","sexe":"H","parlementaire_groupe_acronyme":"NI","fonction":"","source":"http://www.assemblee-nationale.fr/15/cri/2017-2018/20180174.asp#P1219301","groupes":["NI"],"nb_cars":44,"nb_excl":1,"nb_qust":0,"nb_phrs":1,"nb_mwbp":44,"interruption":true},{"id":"176765","seance_id":"1200","date":"2018-04-03","moment":"15:00","type":"elocution","titre":"demande de constitution d'une commission spéciale","titre_complet":"demande de constitution d'une commission spéciale","timestamp":"4920","intervention":"<p>Nous sommes ravis, monsieur Lassalle, de prendre connaissance de vos intentions.</p>","nb_mots":13,"nom":"NULL","parlementaire":"Annie Genevard","sexe":"F","parlementaire_groupe_acronyme":"LR","fonction":"présidente","source":"http://www.assemblee-nationale.fr/15/cri/2017-2018/20180174.asp#P1219302","groupes":["présidence"],"nb_cars":87,"nb_excl":0,"nb_qust":0,"nb_phrs":1,"nb_mwbp":87,"interruption":false},{"id":"176766","seance_id":"1200","date":"2018-04-03","moment":"15:00","type":"didascalie","titre":"demande de constitution d'une commission spéciale","titre_complet":"demande de constitution d'une commission spéciale","timestamp":"4930","intervention":"<p>Nous sommes ravis, monsieur Lassalle, de prendre connaissance de vos intentions.</p>","nb_mots":13,"nom":"NULL","parlementaire":"Annie Genevard","sexe":"F","parlementaire_groupe_acronyme":"LR","fonction":"présidente","source":"http://www.assemblee-nationale.fr/15/cri/2017-2018/20180174.asp#P1219302","didascalie":"Rires et applaudissements sur les bancs du groupe LaREM","groups":"LREM","parlementaire_groupe_norme":"LR","ton":"positif","groupes":["LREM"],"nb_cars":87,"nb_excl":0,"nb_qust":0,"nb_phrs":1,"nb_mwbp":87,"interruption":true},{"id":"176767","seance_id":"1200","date":"2018-04-03","moment":"15:00","type":"elocution","titre":"demande de constitution d'une commission spéciale","titre_complet":"demande de constitution d'une commission spéciale","timestamp":"4940","intervention":"<p>La parole est à Mme la présidente de la commission des affaires sociales, auteure de l'opposition.</p>","nb_mots":19,"nom":"NULL","parlementaire":"Annie Genevard","sexe":"F","parlementaire_groupe_acronyme":"LR","fonction":"présidente","source":"http://www.assemblee-nationale.fr/15/cri/2017-2018/20180174.asp#P1219302","groupes":["présidence"],"nb_cars":105,"nb_excl":0,"nb_qust":0,"nb_phrs":1,"nb_mwbp":105,"interruption":false},{"id":"176768","seance_id":"1200","date":"2018-04-03","moment":"15:00","type":"elocution","titre":"demande de constitution d'une commission spéciale","titre_complet":"demande de constitution d'une commission spéciale","timestamp":"4950","intervention":"<p>Madame la présidente, monsieur le président Chassaigne, mes chers collègues, le président du groupe GDR a déposé, mercredi dernier, une demande tendant à la création d'une commission spéciale sur la proposition de loi no 805 portant suppression de la prise en compte des revenus du conjoint dans la base de calcul de l'allocation aux adultes handicapés, l'AAH.</p>","nb_mots":62,"nom":"NULL","parlementaire":"Brigitte Bourguignon","sexe":"F","parlementaire_groupe_acronyme":"LREM","fonction":"présidente de la commission des affaires sociales","source":"http://www.assemblee-nationale.fr/15/cri/2017-2018/20180174.asp#P1219304","groupes":["commission"],"nb_cars":367,"nb_excl":0,"nb_qust":0,"nb_phrs":1,"nb_mwbp":367,"interruption":false},{"id":"176769","seance_id":"1200","date":"2018-04-03","moment":"15:00","type":"elocution","titre":"demande de constitution d'une commission spéciale","titre_complet":"demande de constitution d'une commission spéciale","timestamp":"4960","intervention":"<p>Très bien !</p>","nb_mots":4,"nom":"NULL","parlementaire":"Valérie Rabault","sexe":"F","parlementaire_groupe_acronyme":"NG","fonction":"","source":"http://www.assemblee-nationale.fr/15/cri/2017-2018/20180174.asp#P1219305","groupes":["NG"],"nb_cars":18,"nb_excl":1,"nb_qust":0,"nb_phrs":1,"nb_mwbp":18,"interruption":true},{"id":"176770","seance_id":"1200","date":"2018-04-03","moment":"15:00","type":"elocution","titre":"demande de constitution d'une commission spéciale","titre_complet":"demande de constitution d'une commission spéciale","timestamp":"4970","intervention":"<p>Il ne m'appartient pas, il ne nous appartient pas, de statuer aujourd'hui sur l'opportunité de l'examen ou de l'adoption d'une telle proposition de loi. En revanche, il nous incombe d'assurer son examen dans les meilleures conditions.</p><p>Ce texte, monsieur le président Chassaigne, vise à modifier les modalités de calcul d'un minimum social destiné aux personnes handicapées, modalités déterminées par le code de la Sécurité sociale. Je ne puis que rappeler les termes de l'article 36, alinéa 10, de notre règlement, qui confie explicitement cette compétence à la commission des affaires sociales de notre assemblée.</p><p>Cette commission a d'ailleurs, depuis le début de la présente législature, montré à plusieurs reprises qu'elle voulait faire avancer la situation des personnes handicapées : elle l'a fait, en dernier lieu, avec la création, en son sein, de référents qui doivent être nos vigies, nos aiguillons dans l'ensemble de nos travaux.</p><p>En tant que présidente de cette commission, je ne puis donc que m'opposer, en application de l'article 31, alinéa 3, de notre règlement, à la demande de constitution d'une commission spéciale.</p>","nb_mots":199,"nom":"NULL","parlementaire":"Brigitte Bourguignon","sexe":"F","parlementaire_groupe_acronyme":"LREM","fonction":"présidente de la commission des affaires sociales","source":"http://www.assemblee-nationale.fr/15/cri/2017-2018/20180174.asp#P1219306","groupes":["commission"],"nb_cars":1158,"nb_excl":0,"nb_qust":0,"nb_phrs":3,"nb_mwbp":386,"interruption":false},{"id":"176771","seance_id":"1200","date":"2018-04-03","moment":"15:00","type":"didascalie","titre":"demande de constitution d'une commission spéciale","titre_complet":"demande de constitution d'une commission spéciale","timestamp":"4980","intervention":"<p>Il ne m'appartient pas, il ne nous appartient pas, de statuer aujourd'hui sur l'opportunité de l'examen ou de l'adoption d'une telle proposition de loi. En revanche, il nous incombe d'assurer son examen dans les meilleures conditions.</p><p>Ce texte, monsieur le président Chassaigne, vise à modifier les modalités de calcul d'un minimum social destiné aux personnes handicapées, modalités déterminées par le code de la Sécurité sociale. Je ne puis que rappeler les termes de l'article 36, alinéa 10, de notre règlement, qui confie explicitement cette compétence à la commission des affaires sociales de notre assemblée.</p><p>Cette commission a d'ailleurs, depuis le début de la présente législature, montré à plusieurs reprises qu'elle voulait faire avancer la situation des personnes handicapées : elle l'a fait, en dernier lieu, avec la création, en son sein, de référents qui doivent être nos vigies, nos aiguillons dans l'ensemble de nos travaux.</p><p>En tant que présidente de cette commission, je ne puis donc que m'opposer, en application de l'article 31, alinéa 3, de notre règlement, à la demande de constitution d'une commission spéciale.</p>","nb_mots":199,"nom":"NULL","parlementaire":"Brigitte Bourguignon","sexe":"F","parlementaire_groupe_acronyme":"LREM","fonction":"présidente de la commission des affaires sociales","source":"http://www.assemblee-nationale.fr/15/cri/2017-2018/20180174.asp#P1219306","didascalie":"Applaudissements sur plusieurs bancs du groupe LaREM","groups":"LREM","parlementaire_groupe_norme":"LREM","ton":"neutre","groupes":["LREM"],"nb_cars":1158,"nb_excl":0,"nb_qust":0,"nb_phrs":3,"nb_mwbp":386,"interruption":true},{"id":"176772","seance_id":"1200","date":"2018-04-03","moment":"15:00","type":"elocution","titre":"demande de constitution d'une commission spéciale","titre_complet":"demande de constitution d'une commission spéciale","timestamp":"4990","intervention":"<p>Pour ma part, je suis d'accord avec cette demande !</p>","nb_mots":12,"nom":"NULL","parlementaire":"Jean Lassalle","sexe":"H","parlementaire_groupe_acronyme":"NI","fonction":"","source":"http://www.assemblee-nationale.fr/15/cri/2017-2018/20180174.asp#P1219310","groupes":["NI"],"nb_cars":58,"nb_excl":1,"nb_qust":0,"nb_phrs":1,"nb_mwbp":58,"interruption":true},{"id":"176773","seance_id":"1200","date":"2018-04-03","moment":"15:00","type":"elocution","titre":"demande de constitution d'une commission spéciale","titre_complet":"demande de constitution d'une commission spéciale","timestamp":"5000","intervention":"<p>Sur le vote de la demande de création d'une commission spéciale, je suis saisie par le groupe de la Gauche démocrate et républicaine d'une demande de scrutin public.</p><p>Le scrutin est annoncé dans l'enceinte de l'Assemblée nationale.</p><p>La parole est à M. André Chassaigne, président du groupe de la Gauche démocrate et républicaine, auteur de la demande de constitution d'une commission spéciale.</p>","nb_mots":73,"nom":"NULL","parlementaire":"Annie Genevard","sexe":"F","parlementaire_groupe_acronyme":"LR","fonction":"présidente","source":"http://www.assemblee-nationale.fr/15/cri/2017-2018/20180174.asp#P1219311","groupes":["présidence"],"nb_cars":410,"nb_excl":0,"nb_qust":0,"nb_phrs":1,"nb_mwbp":410,"interruption":false},{"id":"176774","seance_id":"1200","date":"2018-04-03","moment":"15:00","type":"elocution","titre":"demande de constitution d'une commission spéciale","titre_complet":"demande de constitution d'une commission spéciale","timestamp":"5010","intervention":"<p>Madame la présidente, madame la présidente de la commission des affaires sociales, mes chers collègues, cela fait des années que les personnes en situation de handicap et les associations qui défendent leurs droits réclament que l'allocation aux adultes handicapés devienne réellement une allocation d'autonomie, et que soit mis fin, pour ce faire, à la prise en compte des revenus de la conjointe ou du conjoint dans son versement. Ce mode de calcul injuste prive de ressources propres des dizaines de milliers de bénéficiaires de l'AAH, pour la seule raison qu'ils vivent avec la personne qu'ils aiment.</p>","nb_mots":103,"nom":"NULL","parlementaire":"André Chassaigne","sexe":"H","parlementaire_groupe_acronyme":"GDR","fonction":"","source":"http://www.assemblee-nationale.fr/15/cri/2017-2018/20180174.asp#P1219313","groupes":["GDR"],"nb_cars":612,"nb_excl":0,"nb_qust":0,"nb_phrs":2,"nb_mwbp":306,"interruption":false},{"id":"176775","seance_id":"1200","date":"2018-04-03","moment":"15:00","type":"elocution","titre":"demande de constitution d'une commission spéciale","titre_complet":"demande de constitution d'une commission spéciale","timestamp":"5020","intervention":"<p>Absolument !</p>","nb_mots":3,"nom":"NULL","parlementaire":"Isabelle Valentin","sexe":"F","parlementaire_groupe_acronyme":"LR","fonction":"","source":"http://www.assemblee-nationale.fr/15/cri/2017-2018/20180174.asp#P1219314","groupes":["LR"],"nb_cars":19,"nb_excl":1,"nb_qust":0,"nb_phrs":1,"nb_mwbp":19,"interruption":true},{"id":"176776","seance_id":"1200","date":"2018-04-03","moment":"15:00","type":"elocution","titre":"demande de constitution d'une commission spéciale","titre_complet":"demande de constitution d'une commission spéciale","timestamp":"5030","intervention":"<p>Je rappelle les chiffres. Si le conjoint ou la conjointe gagne 1 126 euros par mois, l'allocation de 810 euros diminue progressivement ; s'il gagne 2 200 euros, le versement de l'AAH est totalement supprimé et l'allocataire n'a plus aucune ressource propre. L'allocation d'autonomie porte décidément mal son nom.</p><p>Nous avons toutes et tous été interpellés par les associations ou par des bénéficiaires de l'AAH sur ce mode de calcul totalement injuste. Il faut agir vite, et c'est au Parlement qu'il revient de le faire, sans tergiverser. Tel est le sens de la proposition de loi portée depuis des mois par Marie-George Buffet et désormais soutenue par plus de quatre-vingts députés issus de tous les groupes politiques, de la majorité comme de l'opposition.</p>","nb_mots":139,"nom":"NULL","parlementaire":"André Chassaigne","sexe":"H","parlementaire_groupe_acronyme":"GDR","fonction":"","source":"http://www.assemblee-nationale.fr/15/cri/2017-2018/20180174.asp#P1219315","groupes":["GDR"],"nb_cars":770,"nb_excl":0,"nb_qust":0,"nb_phrs":5,"nb_mwbp":154,"interruption":false},{"id":"176777","seance_id":"1200","date":"2018-04-03","moment":"15:00","type":"didascalie","titre":"demande de constitution d'une commission spéciale","titre_complet":"demande de constitution d'une commission spéciale","timestamp":"5040","intervention":"<p>Je rappelle les chiffres. Si le conjoint ou la conjointe gagne 1 126 euros par mois, l'allocation de 810 euros diminue progressivement ; s'il gagne 2 200 euros, le versement de l'AAH est totalement supprimé et l'allocataire n'a plus aucune ressource propre. L'allocation d'autonomie porte décidément mal son nom.</p><p>Nous avons toutes et tous été interpellés par les associations ou par des bénéficiaires de l'AAH sur ce mode de calcul totalement injuste. Il faut agir vite, et c'est au Parlement qu'il revient de le faire, sans tergiverser. Tel est le sens de la proposition de loi portée depuis des mois par Marie-George Buffet et désormais soutenue par plus de quatre-vingts députés issus de tous les groupes politiques, de la majorité comme de l'opposition.</p>","nb_mots":139,"nom":"NULL","parlementaire":"André Chassaigne","sexe":"H","parlementaire_groupe_acronyme":"GDR","fonction":"","source":"http://www.assemblee-nationale.fr/15/cri/2017-2018/20180174.asp#P1219315","didascalie":"Applaudissements sur les bancs des groupes GDR et FI","groups":"GDR|LFI","parlementaire_groupe_norme":"GDR","ton":"neutre","groupes":["GDR","LFI"],"nb_cars":770,"nb_excl":0,"nb_qust":0,"nb_phrs":5,"nb_mwbp":154,"interruption":true},{"id":"176778","seance_id":"1200","date":"2018-04-03","moment":"15:00","type":"elocution","titre":"demande de constitution d'une commission spéciale","titre_complet":"demande de constitution d'une commission spéciale","timestamp":"5050","intervention":"<p>Très bien !</p>","nb_mots":4,"nom":"NULL","parlementaire":"Jean Lassalle","sexe":"H","parlementaire_groupe_acronyme":"NI","fonction":"","source":"http://www.assemblee-nationale.fr/15/cri/2017-2018/20180174.asp#P1219317","groupes":["NI"],"nb_cars":18,"nb_excl":1,"nb_qust":0,"nb_phrs":1,"nb_mwbp":18,"interruption":true},{"id":"176779","seance_id":"1200","date":"2018-04-03","moment":"15:00","type":"elocution","titre":"demande de constitution d'une commission spéciale","titre_complet":"demande de constitution d'une commission spéciale","timestamp":"5060","intervention":"<p>Cette proposition de loi transpartisane doit être inscrite à l'ordre du jour de l'Assemblée nationale le plus rapidement possible. La constitution d'une commission spéciale serait un geste fort. Nous montrerions ainsi que les députés écoutent les attentes sociales et dépassent les clivages quand il faut prendre des mesures de justice et de bon sens.</p><p>Mais nous savons toutes et tous, ici, les raisons de l'opposition à l'étude de ce texte : il va à rebours des orientations du Gouvernement qui, lui, propose que les revenus du conjoint soient encore davantage pris en compte dans le versement de l'AAH, en portant le coefficient qui lui est appliqué de 2 à 1,8, afin de le rapprocher de celui du revenu de solidarité active – RSA.</p><p>Or, pour bien comprendre ce qui plaide en faveur d'une individualisation du droit à l'AAH, il faut rappeler la nature et la fonction de cette allocation, qui n'est en rien comparable au RSA. L'AAH n'est pas un minimum social mais une allocation d'autonomie destinée aux personnes qui, en raison de leur handicap, ne peuvent exercer une activité normale et tirer des revenus suffisants de leur travail.</p><p>De plus, cette proposition de loi est indispensable pour donner sa pleine mesure à l'augmentation de l'AAH à 900 euros décidée par le Gouvernement.</p>","nb_mots":234,"nom":"NULL","parlementaire":"André Chassaigne","sexe":"H","parlementaire_groupe_acronyme":"GDR","fonction":"","source":"http://www.assemblee-nationale.fr/15/cri/2017-2018/20180174.asp#P1219318","groupes":["GDR"],"nb_cars":1306,"nb_excl":0,"nb_qust":0,"nb_phrs":4,"nb_mwbp":326.5,"interruption":false},{"id":"176780","seance_id":"1200","date":"2018-04-03","moment":"15:00","type":"didascalie","titre":"demande de constitution d'une commission spéciale","titre_complet":"demande de constitution d'une commission spéciale","timestamp":"5070","intervention":"<p>Cette proposition de loi transpartisane doit être inscrite à l'ordre du jour de l'Assemblée nationale le plus rapidement possible. La constitution d'une commission spéciale serait un geste fort. Nous montrerions ainsi que les députés écoutent les attentes sociales et dépassent les clivages quand il faut prendre des mesures de justice et de bon sens.</p><p>Mais nous savons toutes et tous, ici, les raisons de l'opposition à l'étude de ce texte : il va à rebours des orientations du Gouvernement qui, lui, propose que les revenus du conjoint soient encore davantage pris en compte dans le versement de l'AAH, en portant le coefficient qui lui est appliqué de 2 à 1,8, afin de le rapprocher de celui du revenu de solidarité active – RSA.</p><p>Or, pour bien comprendre ce qui plaide en faveur d'une individualisation du droit à l'AAH, il faut rappeler la nature et la fonction de cette allocation, qui n'est en rien comparable au RSA. L'AAH n'est pas un minimum social mais une allocation d'autonomie destinée aux personnes qui, en raison de leur handicap, ne peuvent exercer une activité normale et tirer des revenus suffisants de leur travail.</p><p>De plus, cette proposition de loi est indispensable pour donner sa pleine mesure à l'augmentation de l'AAH à 900 euros décidée par le Gouvernement.</p>","nb_mots":234,"nom":"NULL","parlementaire":"André Chassaigne","sexe":"H","parlementaire_groupe_acronyme":"GDR","fonction":"","source":"http://www.assemblee-nationale.fr/15/cri/2017-2018/20180174.asp#P1219318","didascalie":"Applaudissements sur les bancs des groupes GDR et NG, ainsi que sur plusieurs bancs des groupes FI et LR","groups":"GDR|LFI|LR|NG","parlementaire_groupe_norme":"GDR","ton":"neutre","groupes":["GDR","LFI","LR","NG"],"nb_cars":1306,"nb_excl":0,"nb_qust":0,"nb_phrs":4,"nb_mwbp":326.5,"interruption":true},{"id":"176781","seance_id":"1200","date":"2018-04-03","moment":"15:00","type":"elocution","titre":"demande de constitution d'une commission spéciale","titre_complet":"demande de constitution d'une commission spéciale","timestamp":"5080","intervention":"<p>En effet, le plafond de ressources pour bénéficier de l'AAH équivaut aujourd'hui à deux fois son montant, qui est de 810 euros. Mais en portant l'AAH à 900 euros, le Gouvernement entend aussi mettre en place un coefficient de 1,8. Au final, le plafond de ressources, pour les personnes qui vivent en couple, sera donc exactement le même qu'aujourd'hui.</p>","nb_mots":67,"nom":"NULL","parlementaire":"André Chassaigne","sexe":"H","parlementaire_groupe_acronyme":"GDR","fonction":"","source":"http://www.assemblee-nationale.fr/15/cri/2017-2018/20180174.asp#P1219318","groupes":["GDR"],"nb_cars":359,"nb_excl":0,"nb_qust":0,"nb_phrs":3,"nb_mwbp":119.66666666666667,"interruption":false},{"id":"176782","seance_id":"1200","date":"2018-04-03","moment":"15:00","type":"elocution","titre":"demande de constitution d'une commission spéciale","titre_complet":"demande de constitution d'une commission spéciale","timestamp":"5090","intervention":"<p>Eh oui, c'est exactement ce que j'avais dit !</p>","nb_mots":12,"nom":"NULL","parlementaire":"Gilles Lurton","sexe":"H","parlementaire_groupe_acronyme":"LR","fonction":"","source":"http://www.assemblee-nationale.fr/15/cri/2017-2018/20180174.asp#P1219322","groupes":["LR"],"nb_cars":52,"nb_excl":1,"nb_qust":0,"nb_phrs":1,"nb_mwbp":52,"interruption":true},{"id":"176783","seance_id":"1200","date":"2018-04-03","moment":"15:00","type":"elocution","titre":"demande de constitution d'une commission spéciale","titre_complet":"demande de constitution d'une commission spéciale","timestamp":"5100","intervention":"<p>En effet, si vous multipliez par deux les 810 euros actuels, ou si vous multipliez les futurs 900 euros par 1,8, vous obtenez la même somme : 1 620 euros. Par ce tour de passe-passe, l'augmentation de l'AAH n'aura aucun effet pour des dizaines de milliers de bénéficiaires qui vivent en couple.</p>","nb_mots":58,"nom":"NULL","parlementaire":"André Chassaigne","sexe":"H","parlementaire_groupe_acronyme":"GDR","fonction":"","source":"http://www.assemblee-nationale.fr/15/cri/2017-2018/20180174.asp#P1219323","groupes":["GDR"],"nb_cars":301,"nb_excl":0,"nb_qust":0,"nb_phrs":2,"nb_mwbp":150.5,"interruption":false},{"id":"176784","seance_id":"1200","date":"2018-04-03","moment":"15:00","type":"didascalie","titre":"demande de constitution d'une commission spéciale","titre_complet":"demande de constitution d'une commission spéciale","timestamp":"5110","intervention":"<p>En effet, si vous multipliez par deux les 810 euros actuels, ou si vous multipliez les futurs 900 euros par 1,8, vous obtenez la même somme : 1 620 euros. Par ce tour de passe-passe, l'augmentation de l'AAH n'aura aucun effet pour des dizaines de milliers de bénéficiaires qui vivent en couple.</p>","nb_mots":58,"nom":"NULL","parlementaire":"André Chassaigne","sexe":"H","parlementaire_groupe_acronyme":"GDR","fonction":"","source":"http://www.assemblee-nationale.fr/15/cri/2017-2018/20180174.asp#P1219323","didascalie":"Applaudissements sur les bancs des groupes GDR et NG, ainsi que sur plusieurs bancs des groupes FI","groups":"GDR|LFI|NG","parlementaire_groupe_norme":"GDR","ton":"neutre","groupes":["GDR","LFI","NG"],"nb_cars":301,"nb_excl":0,"nb_qust":0,"nb_phrs":2,"nb_mwbp":150.5,"interruption":true},{"id":"176785","seance_id":"1200","date":"2018-04-03","moment":"15:00","type":"elocution","titre":"demande de constitution d'une commission spéciale","titre_complet":"demande de constitution d'une commission spéciale","timestamp":"5120","intervention":"<p>Très juste !</p>","nb_mots":4,"nom":"NULL","parlementaire":"Gilles Lurton","sexe":"H","parlementaire_groupe_acronyme":"LR","fonction":"","source":"http://www.assemblee-nationale.fr/15/cri/2017-2018/20180174.asp#P1219324","groupes":["LR"],"nb_cars":19,"nb_excl":1,"nb_qust":0,"nb_phrs":1,"nb_mwbp":19,"interruption":true},{"id":"176786","seance_id":"1200","date":"2018-04-03","moment":"15:00","type":"elocution","titre":"demande de constitution d'une commission spéciale","titre_complet":"demande de constitution d'une commission spéciale","timestamp":"5130","intervention":"<p>Mes chers collègues, la constitution d'une commission spéciale est tout autant un moyen qu'une fin. Elle est une fin, car, comme je l'ai dit, il est urgent d'agir. En effet, 250 000 allocataires vivent en couple. Nous devons entendre la détresse de ceux qui perdent leurs revenus ; nous devons agir pour ceux qui renoncent à leur vie privée pour conserver leur autonomie financière. Cet acte serait aussi une façon de montrer la puissance du Parlement quand les députés oeuvrent de concert pour l'intérêt général.</p><p>Face aux mesquineries comptables, face aux économies de bouts de chandelle qui ont trop tendance à guider l'action publique, nous devons, en tant que représentants du peuple, être à l'écoute des demandes sociales et agir concrètement, chaque fois que c'est nécessaire, pour améliorer la vie des gens.</p><p>Cette proposition de loi est porteuse d'union et peut être la source d'un beau travail en commun. Nous sommes aujourd'hui quatre-vingts députés, issus de tous les bancs, à l'avoir déposée et nous pouvons trouver sans difficulté une majorité pour qu'elle soit adoptée.</p><p>Aujourd'hui, la présidente de la commission des affaires sociales s'oppose à la constitution d'une commission spéciale, sans nous garantir qu'elle mettra toute son énergie pour inscrire ce texte à l'ordre du jour de la commission, ce que nous interprétons comme une opposition à son examen.</p><p>Chers collègues, étudions, débattons, complétons, votons ce texte ! Il changera les vies de dizaines de milliers de nos concitoyens et concitoyennes en situation de handicap ! Commençons cet ouvrage en votant en faveur de la création de cette commission spéciale, qui nous permettra de nous mettre concrètement – je dis bien, concrètement – au travail !</p>","nb_mots":299,"nom":"NULL","parlementaire":"André Chassaigne","sexe":"H","parlementaire_groupe_acronyme":"GDR","fonction":"","source":"http://www.assemblee-nationale.fr/15/cri/2017-2018/20180174.asp#P1219325","groupes":["GDR"],"nb_cars":1758,"nb_excl":3,"nb_qust":0,"nb_phrs":8,"nb_mwbp":219.75,"interruption":false},{"id":"176787","seance_id":"1200","date":"2018-04-03","moment":"15:00","type":"didascalie","titre":"demande de constitution d'une commission spéciale","titre_complet":"demande de constitution d'une commission spéciale","timestamp":"5140","intervention":"<p>Mes chers collègues, la constitution d'une commission spéciale est tout autant un moyen qu'une fin. Elle est une fin, car, comme je l'ai dit, il est urgent d'agir. En effet, 250 000 allocataires vivent en couple. Nous devons entendre la détresse de ceux qui perdent leurs revenus ; nous devons agir pour ceux qui renoncent à leur vie privée pour conserver leur autonomie financière. Cet acte serait aussi une façon de montrer la puissance du Parlement quand les députés oeuvrent de concert pour l'intérêt général.</p><p>Face aux mesquineries comptables, face aux économies de bouts de chandelle qui ont trop tendance à guider l'action publique, nous devons, en tant que représentants du peuple, être à l'écoute des demandes sociales et agir concrètement, chaque fois que c'est nécessaire, pour améliorer la vie des gens.</p><p>Cette proposition de loi est porteuse d'union et peut être la source d'un beau travail en commun. Nous sommes aujourd'hui quatre-vingts députés, issus de tous les bancs, à l'avoir déposée et nous pouvons trouver sans difficulté une majorité pour qu'elle soit adoptée.</p><p>Aujourd'hui, la présidente de la commission des affaires sociales s'oppose à la constitution d'une commission spéciale, sans nous garantir qu'elle mettra toute son énergie pour inscrire ce texte à l'ordre du jour de la commission, ce que nous interprétons comme une opposition à son examen.</p><p>Chers collègues, étudions, débattons, complétons, votons ce texte ! Il changera les vies de dizaines de milliers de nos concitoyens et concitoyennes en situation de handicap ! Commençons cet ouvrage en votant en faveur de la création de cette commission spéciale, qui nous permettra de nous mettre concrètement – je dis bien, concrètement – au travail !</p>","nb_mots":299,"nom":"NULL","parlementaire":"André Chassaigne","sexe":"H","parlementaire_groupe_acronyme":"GDR","fonction":"","source":"http://www.assemblee-nationale.fr/15/cri/2017-2018/20180174.asp#P1219325","didascalie":"Applaudissements sur les bancs des groupes GDR, FI, NG et LR","groups":"GDR|LFI|LR|NG","parlementaire_groupe_norme":"GDR","ton":"neutre","groupes":["GDR","LFI","LR","NG"],"nb_cars":1758,"nb_excl":3,"nb_qust":0,"nb_phrs":8,"nb_mwbp":219.75,"interruption":true},{"id":"176789","seance_id":"1200","date":"2018-04-03","moment":"15:00","type":"elocution","titre":"vote sur la constitution d'une commission spéciale","titre_complet":"demande de constitution d'une commission spéciale > vote sur la constitution d'une commission spéciale","timestamp":"5160","intervention":"<p>Je mets aux voix la demande de constitution d'une commission spéciale.</p>","nb_mots":14,"nom":"NULL","parlementaire":"Annie Genevard","sexe":"F","parlementaire_groupe_acronyme":"LR","fonction":"présidente","source":"http://www.assemblee-nationale.fr/15/cri/2017-2018/20180174.asp#P1219223","groupes":["présidence"],"nb_cars":77,"nb_excl":0,"nb_qust":0,"nb_phrs":1,"nb_mwbp":77,"interruption":false},{"id":"176791","seance_id":"1200","date":"2018-04-03","moment":"15:00","type":"elocution","titre":"vote sur la constitution d'une commission spéciale","titre_complet":"demande de constitution d'une commission spéciale > vote sur la constitution d'une commission spéciale","timestamp":"5180","intervention":"<p>Voici le résultat du scrutin :</p>","nb_mots":7,"nom":"NULL","parlementaire":"Annie Genevard","sexe":"F","parlementaire_groupe_acronyme":"LR","fonction":"présidente","source":"http://www.assemblee-nationale.fr/15/cri/2017-2018/20180174.asp#P1219223","groupes":["présidence"],"nb_cars":37,"nb_excl":0,"nb_qust":0,"nb_phrs":1,"nb_mwbp":37,"interruption":false},{"id":"176793","seance_id":"1200","date":"2018-04-03","moment":"15:00","type":"didascalie","titre":"vote sur la constitution d'une commission spéciale","titre_complet":"demande de constitution d'une commission spéciale > vote sur la constitution d'une commission spéciale","timestamp":"5200","intervention":"<p>Voici le résultat du scrutin :</p>","nb_mots":7,"nom":"NULL","parlementaire":"Annie Genevard","sexe":"F","parlementaire_groupe_acronyme":"LR","fonction":"présidente","source":"http://www.assemblee-nationale.fr/15/cri/2017-2018/20180174.asp#P1219223","didascalie":"La demande de constitution d'une commission spéciale n'est pas adoptée","groups":"","parlementaire_groupe_norme":"LR","ton":"neutre","groupes":[""],"nb_cars":37,"nb_excl":0,"nb_qust":0,"nb_phrs":1,"nb_mwbp":37,"interruption":true},{"id":"176794","seance_id":"1200","date":"2018-04-03","moment":"15:00","type":"elocution","titre":"vote sur la constitution d'une commission spéciale","titre_complet":"demande de constitution d'une commission spéciale > vote sur la constitution d'une commission spéciale","timestamp":"5210","intervention":"<p>En conséquence, la proposition de loi demeure donc renvoyée à la commission des affaires sociales.</p>","nb_mots":17,"nom":"NULL","parlementaire":"Annie Genevard","sexe":"F","parlementaire_groupe_acronyme":"LR","fonction":"présidente","source":"http://www.assemblee-nationale.fr/15/cri/2017-2018/20180174.asp#P1219227","groupes":["présidence"],"nb_cars":105,"nb_excl":0,"nb_qust":0,"nb_phrs":1,"nb_mwbp":105,"interruption":false}],"nb_cars":13776,"nb_mots":2420,"nb_excl":13,"nb_interruptions":14,"pc_interruptions":0.4827586206896552}]}