{"id":"ouverture-de-la-session-ordinaire","nom":"ouverture de la session ordinaire","id_an":null,"metrics":{},"seances":[{"id":"184","sommaire":[],"parlementaires":{"François de Rugy":1},"personnalites":{},"interventions":[{"id":"38962","seance_id":"184","date":"2017-10-03","moment":"15:00","type":"elocution","titre":"ouverture de la session ordinaire","titre_complet":"ouverture de la session ordinaire","timestamp":"40","intervention":"<p>Conformément au premier alinéa de l'article 28 de la Constitution, j'ai pris acte de l'ouverture de la session ordinaire de 2017-2018 au Journal officiel de ce jour.</p>","nb_mots":33,"nom":"NULL","parlementaire":"François de Rugy","sexe":"H","parlementaire_groupe_acronyme":"LREM","fonction":"président","source":"http://www.assemblee-nationale.fr/15/cri/2017-2018/20180001.asp#P1030251","groupes":["présidence"],"nb_cars":172,"nb_excl":0,"nb_qust":0,"nb_phrs":1,"nb_mwbp":172,"interruption":false}],"nb_cars":172,"nb_mots":33,"nb_excl":0,"nb_interruptions":0,"pc_interruptions":0}]}